vaunix_api/__init__.py
vaunix_api/lsg.py
vaunix_api-0.2.dist-info/METADATA
vaunix_api-0.2.dist-info/RECORD
vaunix_api-0.2.dist-info/WHEEL
vaunix_api-0.2.dist-info/top_level.txt
