Metadata-Version: 2.1
Name: vaunix-api
Version: 0.2
Summary: Wrapper around VNX API to control signal generators, attenuators etc by vaunix
Home-page: https://github.com/qutech/vaunix_api
Maintainer: Simon Humpohl
Maintainer-email: simon.humpohl@rwth-aachen.de
License: GPL
Keywords: vaunix,labbrick
Platform: UNKNOWN
Classifier: Development Status :: 3 - Alpha
Classifier: Intended Audience :: Science/Research
Classifier: Programming Language :: Python :: 3 :: Only
Classifier: Programming Language :: Python :: 3.5
Classifier: Topic :: Scientific/Engineering
